dynamics/__init__.py
dynamics/customerinsights/__init__.py
dynamics/customerinsights/api/__init__.py
dynamics/customerinsights/api/customer_insights.py
dynamics/customerinsights/api/version.py
dynamics/customerinsights/api/models/__init__.py
dynamics/customerinsights/api/models/accepted_result.py
dynamics/customerinsights/api/models/accepted_result_py3.py
dynamics/customerinsights/api/models/activity_source_entity_info.py
dynamics/customerinsights/api/models/activity_source_entity_info_py3.py
dynamics/customerinsights/api/models/annotation.py
dynamics/customerinsights/api/models/annotation_py3.py
dynamics/customerinsights/api/models/api_error_result.py
dynamics/customerinsights/api/models/api_error_result_py3.py
dynamics/customerinsights/api/models/attribute_data_profile.py
dynamics/customerinsights/api/models/attribute_data_profile_py3.py
dynamics/customerinsights/api/models/attribute_search_configuration.py
dynamics/customerinsights/api/models/attribute_search_configuration_py3.py
dynamics/customerinsights/api/models/attribute_search_properties.py
dynamics/customerinsights/api/models/attribute_search_properties_py3.py
dynamics/customerinsights/api/models/attribute_semantic_information.py
dynamics/customerinsights/api/models/attribute_semantic_information_py3.py
dynamics/customerinsights/api/models/banners.py
dynamics/customerinsights/api/models/banners_py3.py
dynamics/customerinsights/api/models/byo_pbi_provisioning_info.py
dynamics/customerinsights/api/models/byo_pbi_provisioning_info_py3.py
dynamics/customerinsights/api/models/cds_mdl_info.py
dynamics/customerinsights/api/models/cds_mdl_info_py3.py
dynamics/customerinsights/api/models/cds_org_info.py
dynamics/customerinsights/api/models/cds_org_info_py3.py
dynamics/customerinsights/api/models/ci_result.py
dynamics/customerinsights/api/models/ci_result_py3.py
dynamics/customerinsights/api/models/coachmarks.py
dynamics/customerinsights/api/models/coachmarks_py3.py
customerinsights-1.0.8.dist-info/LICENSE
customerinsights-1.0.8.dist-info/METADATA
customerinsights-1.0.8.dist-info/WHEEL
customerinsights-1.0.8.dist-info/top_level.txt
customerinsights-1.0.8.dist-info/RECORD
