Metadata-Version: 2.1
Name: customerinsights
Version: 1.0.8
Summary: Client library for interacting with Customer Insights APIs
Home-page: https://developer.ci.ai.dynamics.com/
Author: Microsoft Corp.
Author-email: cihelp@microsoft.com
License: UNKNOWN
Platform: UNKNOWN
Requires-Python: >=2.7
